{
  "form-submissions": [
    {
      "id": "3rn1",
      "firstName": "Cathy",
      "lastName": "Qin",
      "age": "65",
      "gender": "F",
      "work_experience": "6",
      "canada_workex": 0,
      "dep_num": "2",
      "canada_born": "false",
      "citizen_status": "citizen",
      "level_of_schooling": "Some university",
      "fluent_english": "false",
      "reading_english_scale": "10",
      "speaking_english_scale": "9",
      "writing_english_scale": "10",
      "numeracy_scale": "10",
      "computer_scale": "10",
      "transportation_bool": "false",
      "caregiver_bool": "true",
      "housing": "Renting-private",
      "income_source": "Employment",
      "felony_bool": "true",
      "attending_school": "true",
      "currently_employed": "true",
      "substance_use": "true",
      "time_unemployed": "3",
      "need_mental_health_support_bool": "false",
      "last_update": "2024-11-17T06:58:16.586Z"
    },
    {
      "id": "tswj",
      "firstName": "Cathy",
      "lastName": "Qin",
      "age": "20",
      "gender": "M",
      "work_experience": "2",
      "canada_workex": 0,
      "dep_num": "3",
      "canada_born": "true",
      "citizen_status": "",
      "level_of_schooling": "",
      "fluent_english": "false",
      "reading_english_scale": "10",
      "speaking_english_scale": "10",
      "writing_english_scale": "10",
      "numeracy_scale": 0,
      "computer_scale": "10",
      "transportation_bool": "false",
      "caregiver_bool": "false",
      "housing": "",
      "income_source": "Employment",
      "felony_bool": "true",
      "attending_school": "true",
      "currently_employed": "false",
      "substance_use": "false",
      "time_unemployed": 0,
      "need_mental_health_support_bool": "false",
      "last_update": "2024-11-14T10:25:33.168Z"
    },
    {
      "id": "tswj",
      "firstName": "Cathy",
      "lastName": "Qin",
      "age": "20",
      "gender": "F",
      "work_experience": "2",
      "canada_workex": 0,
      "dep_num": 0,
      "canada_born": "true",
      "citizen_status": "",
      "level_of_schooling": "",
      "fluent_english": "false",
      "reading_english_scale": "10",
      "speaking_english_scale": "10",
      "writing_english_scale": "10",
      "numeracy_scale": 0,
      "computer_scale": "10",
      "transportation_bool": "false",
      "caregiver_bool": "false",
      "housing": "",
      "income_source": "",
      "felony_bool": "false",
      "attending_school": "true",
      "currently_employed": "true",
      "substance_use": "false",
      "time_unemployed": 0,
      "need_mental_health_support_bool": "false",
      "last_update": ""
    },
    {
      "id": "tswj",
      "firstName": "Cathy",
      "lastName": "Qin",
      "age": "24",
      "gender": "F",
      "work_experience": "5",
      "canada_workex": 0,
      "dep_num": 0,
      "canada_born": "true",
      "citizen_status": "",
      "level_of_schooling": "",
      "fluent_english": "false",
      "reading_english_scale": "10",
      "speaking_english_scale": "10",
      "writing_english_scale": "10",
      "numeracy_scale": 0,
      "computer_scale": "10",
      "transportation_bool": "false",
      "caregiver_bool": "false",
      "housing": "",
      "income_source": "",
      "felony_bool": "false",
      "attending_school": "true",
      "currently_employed": "true",
      "substance_use": "false",
      "time_unemployed": 0,
      "need_mental_health_support_bool": "false",
      "last_update": ""
    },
    {
      "id": "tswj",
      "firstName": "Cathy",
      "lastName": "Qin",
      "age": "18",
      "gender": "F",
      "work_experience": "2",
      "canada_workex": 0,
      "dep_num": 0,
      "canada_born": "true",
      "citizen_status": "",
      "level_of_schooling": "",
      "fluent_english": "true",
      "reading_english_scale": "10",
      "speaking_english_scale": "10",
      "writing_english_scale": "10",
      "numeracy_scale": 0,
      "computer_scale": "10",
      "transportation_bool": "false",
      "caregiver_bool": "false",
      "housing": "",
      "income_source": "",
      "felony_bool": "false",
      "attending_school": "true",
      "currently_employed": "true",
      "substance_use": "false",
      "time_unemployed": 0,
      "need_mental_health_support_bool": "false",
      "last_update": ""
    },
    {
      "id": "tswj",
      "firstName": "Cathy",
      "lastName": "Qin",
      "age": "20",
      "gender": "F",
      "work_experience": "0",
      "canada_workex": 0,
      "dep_num": 1,
      "canada_born": "false",
      "citizen_status": "",
      "level_of_schooling": "",
      "fluent_english": "false",
      "reading_english_scale": "9",
      "speaking_english_scale": "10",
      "writing_english_scale": "10",
      "numeracy_scale": 0,
      "computer_scale": "10",
      "transportation_bool": "false",
      "caregiver_bool": "false",
      "housing": "",
      "income_source": "",
      "felony_bool": "false",
      "attending_school": "true",
      "currently_employed": "true",
      "substance_use": "false",
      "time_unemployed": 0,
      "need_mental_health_support_bool": "false",
      "last_update": ""
    },
    {
      "id": "57kl",
      "firstName": "Xujia",
      "lastName": "",
      "age": "22",
      "gender": "",
      "work_experience": 0,
      "canada_workex": 0,
      "dep_num": 0,
      "canada_born": "false",
      "citizen_status": "",
      "level_of_schooling": "",
      "fluent_english": "false",
      "reading_english_scale": 0,
      "speaking_english_scale": 0,
      "writing_english_scale": 0,
      "numeracy_scale": 0,
      "computer_scale": 0,
      "transportation_bool": "false",
      "caregiver_bool": "false",
      "housing": "",
      "income_source": "",
      "felony_bool": "false",
      "attending_school": "false",
      "currently_employed": "false",
      "substance_use": "false",
      "time_unemployed": 0,
      "need_mental_health_support_bool": "false",
      "last_update": ""
    },
    {
      "id": "mx5h",
      "firstName": "",
      "lastName": "",
      "age": "18",
      "gender": "",
      "work_experience": 0,
      "canada_workex": 0,
      "dep_num": 0,
      "canada_born": "false",
      "citizen_status": "",
      "level_of_schooling": "",
      "fluent_english": "false",
      "reading_english_scale": 0,
      "speaking_english_scale": 0,
      "writing_english_scale": 0,
      "numeracy_scale": 0,
      "computer_scale": 0,
      "transportation_bool": "false",
      "caregiver_bool": "false",
      "housing": "",
      "income_source": "",
      "felony_bool": "false",
      "attending_school": "false",
      "currently_employed": "false",
      "substance_use": "false",
      "time_unemployed": 0,
      "need_mental_health_support_bool": "false",
      "last_update": ""
    },
    {
      "id": "jjp3",
      "firstName": "Juwon",
      "lastName": "",
      "age": "",
      "gender": "",
      "work_experience": 0,
      "canada_workex": 0,
      "dep_num": 0,
      "canada_born": "false",
      "citizen_status": "",
      "level_of_schooling": "",
      "fluent_english": "false",
      "reading_english_scale": 0,
      "speaking_english_scale": 0,
      "writing_english_scale": 0,
      "numeracy_scale": 0,
      "computer_scale": 0,
      "transportation_bool": "false",
      "caregiver_bool": "false",
      "housing": "",
      "income_source": "",
      "felony_bool": "false",
      "attending_school": "false",
      "currently_employed": "false",
      "substance_use": "false",
      "time_unemployed": 0,
      "need_mental_health_support_bool": "false"
    },
    {
      "id": "lqvp",
      "firstName": "",
      "lastName": "",
      "age": "64",
      "gender": "",
      "work_experience": 0,
      "canada_workex": 0,
      "dep_num": 0,
      "canada_born": "false",
      "citizen_status": "",
      "level_of_schooling": "",
      "fluent_english": "false",
      "reading_english_scale": 0,
      "speaking_english_scale": 0,
      "writing_english_scale": 0,
      "numeracy_scale": 0,
      "computer_scale": 0,
      "transportation_bool": "false",
      "caregiver_bool": "false",
      "housing": "",
      "income_source": "",
      "felony_bool": "false",
      "attending_school": "false",
      "currently_employed": "false",
      "substance_use": "false",
      "time_unemployed": 0,
      "need_mental_health_support_bool": "false"
    }
  ]
}